upicmedia/API.py
upicmedia/Client.py
upicmedia/__init__.py
upicmedia/upicmedia.py
upicmedia-0.5.dist-info/License
upicmedia-0.5.dist-info/METADATA
upicmedia-0.5.dist-info/WHEEL
upicmedia-0.5.dist-info/top_level.txt
upicmedia-0.5.dist-info/RECORD
