Metadata-Version: 2.1
Name: upicmedia
Version: 0.5
Summary: Python package to get data from the UPIC service with crowdsourced tools
Home-page: https://github.com/upicmi/Upicmedia
Author: Mehrdad Rashidian
Author-email: Mehrdadrashidian70@gmail.com
License: UNKNOWN
Platform: UNKNOWN
Classifier: Programming Language :: Python :: 3
Classifier: License :: OSI Approved :: MIT License
Classifier: Operating System :: OS Independent
Requires-Python: >=3.6
License-File: License
